{
  "Tenders_Page/_next/image/-69" : {
    "transaction" : "Tenders_Page/_next/image/-69",
    "sampleCount" : 100,
    "errorCount" : 6,
    "errorPct" : 6.0,
    "meanResTime" : 252.85000000000002,
    "medianResTime" : 221.5,
    "minResTime" : 0.0,
    "maxResTime" : 1412.0,
    "pct1ResTime" : 352.20000000000005,
    "pct2ResTime" : 485.699999999999,
    "pct3ResTime" : 1406.6899999999973,
    "throughput" : 0.17856058739290828,
    "receivedKBytesPerSec" : 9.05166165134617,
    "sentKBytesPerSec" : 0.08425130215308356
  },
  "Tenders_Page/_next/image/-68" : {
    "transaction" : "Tenders_Page/_next/image/-68",
    "sampleCount" : 100,
    "errorCount" : 6,
    "errorPct" : 6.0,
    "meanResTime" : 241.91000000000003,
    "medianResTime" : 161.0,
    "minResTime" : 0.0,
    "maxResTime" : 2339.0,
    "pct1ResTime" : 317.40000000000003,
    "pct2ResTime" : 675.8999999999997,
    "pct3ResTime" : 2338.84,
    "throughput" : 0.1779511417345254,
    "receivedKBytesPerSec" : 2.0606846481105148,
    "sentKBytesPerSec" : 0.08396374378950515
  },
  "Tenders_Page/maps/streets/256/8/149/88.png-80" : {
    "transaction" : "Tenders_Page/maps/streets/256/8/149/88.png-80",
    "sampleCount" : 100,
    "errorCount" : 0,
    "errorPct" : 0.0,
    "meanResTime" : 308.13000000000005,
    "medianResTime" : 97.0,
    "minResTime" : 39.0,
    "maxResTime" : 8204.0,
    "pct1ResTime" : 440.8000000000001,
    "pct2ResTime" : 1458.499999999999,
    "pct3ResTime" : 8137.499999999966,
    "throughput" : 0.11890564005122455,
    "receivedKBytesPerSec" : 2.322724138617817,
    "sentKBytesPerSec" : 0.05225345510063579
  },
  "Tenders_Page/_next/image/-67" : {
    "transaction" : "Tenders_Page/_next/image/-67",
    "sampleCount" : 100,
    "errorCount" : 6,
    "errorPct" : 6.0,
    "meanResTime" : 149.49999999999997,
    "medianResTime" : 102.0,
    "minResTime" : 0.0,
    "maxResTime" : 717.0,
    "pct1ResTime" : 350.50000000000034,
    "pct2ResTime" : 478.4999999999999,
    "pct3ResTime" : 716.4099999999997,
    "throughput" : 0.17824454081532617,
    "receivedKBytesPerSec" : 2.4791796450972945,
    "sentKBytesPerSec" : 0.08410218001985643
  },
  "Tenders_Page/_next/static/chunks/pages/products/%5Bproduct%5D-b30966a75ae7278d.js-109" : {
    "transaction" : "Tenders_Page/_next/static/chunks/pages/products/%5Bproduct%5D-b30966a75ae7278d.js-109",
    "sampleCount" : 44,
    "errorCount" : 37,
    "errorPct" : 84.09091,
    "meanResTime" : 29764.386363636368,
    "medianResTime" : 55.5,
    "minResTime" : 0.0,
    "maxResTime" : 68296.0,
    "pct1ResTime" : 62095.5,
    "pct2ResTime" : 62102.0,
    "pct3ResTime" : 68296.0,
    "throughput" : 0.026705413794317328,
    "receivedKBytesPerSec" : 0.05872452686655669,
    "sentKBytesPerSec" : 0.0019500357640115417
  },
  "Tenders_Page/_next/static/chunks/pages/products/%5Bproduct%5D-b30966a75ae7278d.js-107" : {
    "transaction" : "Tenders_Page/_next/static/chunks/pages/products/%5Bproduct%5D-b30966a75ae7278d.js-107",
    "sampleCount" : 44,
    "errorCount" : 37,
    "errorPct" : 84.09091,
    "meanResTime" : 29622.363636363632,
    "medianResTime" : 70.0,
    "minResTime" : 0.0,
    "maxResTime" : 62084.0,
    "pct1ResTime" : 62069.0,
    "pct2ResTime" : 62083.75,
    "pct3ResTime" : 62084.0,
    "throughput" : 0.02775013275915786,
    "receivedKBytesPerSec" : 0.061021837344173546,
    "sentKBytesPerSec" : 0.0021211704816792363
  },
  "Tenders_Page/_next/image/-64" : {
    "transaction" : "Tenders_Page/_next/image/-64",
    "sampleCount" : 100,
    "errorCount" : 0,
    "errorPct" : 0.0,
    "meanResTime" : 892.77,
    "medianResTime" : 331.5,
    "minResTime" : 141.0,
    "maxResTime" : 9173.0,
    "pct1ResTime" : 1037.7,
    "pct2ResTime" : 7142.099999999996,
    "pct3ResTime" : 9167.139999999998,
    "throughput" : 0.19831157524833568,
    "receivedKBytesPerSec" : 9.249083382208873,
    "sentKBytesPerSec" : 0.09954311491957474
  },
  "Tenders_Page/_next/image/-63" : {
    "transaction" : "Tenders_Page/_next/image/-63",
    "sampleCount" : 100,
    "errorCount" : 0,
    "errorPct" : 0.0,
    "meanResTime" : 111.26999999999998,
    "medianResTime" : 57.0,
    "minResTime" : 45.0,
    "maxResTime" : 2078.0,
    "pct1ResTime" : 166.8,
    "pct2ResTime" : 230.89999999999975,
    "pct3ResTime" : 2067.659999999995,
    "throughput" : 0.19826124884760649,
    "receivedKBytesPerSec" : 1.39390436496922,
    "sentKBytesPerSec" : 0.09951785342545873
  },
  "Tenders_Page/_next/image/-62" : {
    "transaction" : "Tenders_Page/_next/image/-62",
    "sampleCount" : 100,
    "errorCount" : 0,
    "errorPct" : 0.0,
    "meanResTime" : 215.18999999999997,
    "medianResTime" : 66.0,
    "minResTime" : 47.0,
    "maxResTime" : 4274.0,
    "pct1ResTime" : 632.9,
    "pct2ResTime" : 838.3499999999997,
    "pct3ResTime" : 4247.999999999987,
    "throughput" : 0.19830528305104575,
    "receivedKBytesPerSec" : 2.2488768019753187,
    "sentKBytesPerSec" : 0.09953995653148195
  },
  "Tenders_Page/maps/streets/256/11/1197/689.png-36" : {
    "transaction" : "Tenders_Page/maps/streets/256/11/1197/689.png-36",
    "sampleCount" : 100,
    "errorCount" : 0,
    "errorPct" : 0.0,
    "meanResTime" : 606.4399999999998,
    "medianResTime" : 488.5,
    "minResTime" : 99.0,
    "maxResTime" : 2253.0,
    "pct1ResTime" : 1185.8000000000002,
    "pct2ResTime" : 1509.2999999999997,
    "pct3ResTime" : 2247.7499999999973,
    "throughput" : 10.015022533800702,
    "receivedKBytesPerSec" : 212.33021407110667,
    "sentKBytesPerSec" : 4.430473835753631
  },
  "Tenders_Page/maps/streets/256/8/149/86.png-85" : {
    "transaction" : "Tenders_Page/maps/streets/256/8/149/86.png-85",
    "sampleCount" : 100,
    "errorCount" : 0,
    "errorPct" : 0.0,
    "meanResTime" : 3688.74,
    "medianResTime" : 113.0,
    "minResTime" : 41.0,
    "maxResTime" : 332984.0,
    "pct1ResTime" : 404.0000000000001,
    "pct2ResTime" : 665.2999999999994,
    "pct3ResTime" : 329806.2199999984,
    "throughput" : 0.11889913667336861,
    "receivedKBytesPerSec" : 2.8489347826345433,
    "sentKBytesPerSec" : 0.052250597170913946
  },
  "Tenders_Page/maps/streets/256/8/149/89.png-86" : {
    "transaction" : "Tenders_Page/maps/streets/256/8/149/89.png-86",
    "sampleCount" : 100,
    "errorCount" : 0,
    "errorPct" : 0.0,
    "meanResTime" : 2531.6599999999985,
    "medianResTime" : 107.0,
    "minResTime" : 42.0,
    "maxResTime" : 188922.0,
    "pct1ResTime" : 258.70000000000016,
    "pct2ResTime" : 488.79999999999745,
    "pct3ResTime" : 187384.3599999992,
    "throughput" : 0.11890026764450247,
    "receivedKBytesPerSec" : 1.8522432318995148,
    "sentKBytesPerSec" : 0.05225109417971299
  },
  "Tenders_Page/maps/streets/256/8/150/88.png-84" : {
    "transaction" : "Tenders_Page/maps/streets/256/8/150/88.png-84",
    "sampleCount" : 100,
    "errorCount" : 0,
    "errorPct" : 0.0,
    "meanResTime" : 595.42,
    "medianResTime" : 107.5,
    "minResTime" : 42.0,
    "maxResTime" : 41332.0,
    "pct1ResTime" : 290.5000000000001,
    "pct2ResTime" : 1344.7499999999902,
    "pct3ResTime" : 40939.4599999998,
    "throughput" : 0.1189039434492845,
    "receivedKBytesPerSec" : 1.7489562463214092,
    "sentKBytesPerSec" : 0.05225270952361135
  },
  "Tenders_Page/maps/streets/256/8/150/86.png-88" : {
    "transaction" : "Tenders_Page/maps/streets/256/8/150/86.png-88",
    "sampleCount" : 100,
    "errorCount" : 2,
    "errorPct" : 2.0,
    "meanResTime" : 3424.759999999999,
    "medianResTime" : 102.5,
    "minResTime" : 40.0,
    "maxResTime" : 116948.0,
    "pct1ResTime" : 332.0,
    "pct2ResTime" : 23936.19999999972,
    "pct3ResTime" : 116908.04999999997,
    "throughput" : 0.1188967334311457,
    "receivedKBytesPerSec" : 2.1866340044954855,
    "sentKBytesPerSec" : 0.05120455023743677
  },
  "Tenders_Page/tr/-104" : {
    "transaction" : "Tenders_Page/tr/-104",
    "sampleCount" : 74,
    "errorCount" : 11,
    "errorPct" : 14.864865,
    "meanResTime" : 1553.6351351351352,
    "medianResTime" : 98.5,
    "minResTime" : 0.0,
    "maxResTime" : 79979.0,
    "pct1ResTime" : 951.0,
    "pct2ResTime" : 3690.5,
    "pct3ResTime" : 79979.0,
    "throughput" : 0.05075369233111709,
    "receivedKBytesPerSec" : 0.0306453816369026,
    "sentKBytesPerSec" : 0.027554319953676968
  },
  "Tenders_Page/maps/streets/256/11/1199/689.png-46" : {
    "transaction" : "Tenders_Page/maps/streets/256/11/1199/689.png-46",
    "sampleCount" : 100,
    "errorCount" : 0,
    "errorPct" : 0.0,
    "meanResTime" : 435.80999999999995,
    "medianResTime" : 399.0,
    "minResTime" : 89.0,
    "maxResTime" : 1369.0,
    "pct1ResTime" : 764.4000000000001,
    "pct2ResTime" : 891.0499999999995,
    "pct3ResTime" : 1367.129999999999,
    "throughput" : 10.047221943132723,
    "receivedKBytesPerSec" : 162.73752260624937,
    "sentKBytesPerSec" : 4.4447183010147695
  },
  "Tenders_Page/maps/streets/256/8/151/87.png-92" : {
    "transaction" : "Tenders_Page/maps/streets/256/8/151/87.png-92",
    "sampleCount" : 100,
    "errorCount" : 0,
    "errorPct" : 0.0,
    "meanResTime" : 113.87999999999997,
    "medianResTime" : 78.5,
    "minResTime" : 40.0,
    "maxResTime" : 705.0,
    "pct1ResTime" : 226.90000000000012,
    "pct2ResTime" : 277.39999999999964,
    "pct3ResTime" : 702.2399999999986,
    "throughput" : 0.11886055517388111,
    "receivedKBytesPerSec" : 2.038969250180074,
    "sentKBytesPerSec" : 0.05223364241039697
  },
  "Tenders_Page/maps/streets/256/8/147/86.png-95" : {
    "transaction" : "Tenders_Page/maps/streets/256/8/147/86.png-95",
    "sampleCount" : 100,
    "errorCount" : 0,
    "errorPct" : 0.0,
    "meanResTime" : 116.88000000000005,
    "medianResTime" : 76.0,
    "minResTime" : 40.0,
    "maxResTime" : 712.0,
    "pct1ResTime" : 222.9,
    "pct2ResTime" : 295.8499999999995,
    "pct3ResTime" : 711.91,
    "throughput" : 0.11888358800179277,
    "receivedKBytesPerSec" : 2.163240132067778,
    "sentKBytesPerSec" : 0.052243764258600334
  },
  "Tenders_Page/api/auth/users/348/units/-106" : {
    "transaction" : "Tenders_Page/api/auth/users/348/units/-106",
    "sampleCount" : 62,
    "errorCount" : 62,
    "errorPct" : 100.0,
    "meanResTime" : 382357.16129032266,
    "medianResTime" : 62031.0,
    "minResTime" : 0.0,
    "maxResTime" : 1213754.0,
    "pct1ResTime" : 1213627.6,
    "pct2ResTime" : 1213682.55,
    "pct3ResTime" : 1213754.0,
    "throughput" : 0.03314930124480973,
    "receivedKBytesPerSec" : 0.08093561045641241,
    "sentKBytesPerSec" : 0.002128744033125776
  },
  "Tenders_Page/api/units/map/-56" : {
    "transaction" : "Tenders_Page/api/units/map/-56",
    "sampleCount" : 100,
    "errorCount" : 18,
    "errorPct" : 18.0,
    "meanResTime" : 15247.490000000003,
    "medianResTime" : 4442.0,
    "minResTime" : 170.0,
    "maxResTime" : 60147.0,
    "pct1ResTime" : 60138.0,
    "pct2ResTime" : 60142.0,
    "pct3ResTime" : 60146.99,
    "throughput" : 0.4766330640356522,
    "receivedKBytesPerSec" : 1.5924292050952074,
    "sentKBytesPerSec" : 0.2913791973499201
  },
  "Tenders_Page/maps/streets/256/8/151/88.png-94" : {
    "transaction" : "Tenders_Page/maps/streets/256/8/151/88.png-94",
    "sampleCount" : 100,
    "errorCount" : 0,
    "errorPct" : 0.0,
    "meanResTime" : 114.60000000000001,
    "medianResTime" : 76.5,
    "minResTime" : 41.0,
    "maxResTime" : 502.0,
    "pct1ResTime" : 227.60000000000002,
    "pct2ResTime" : 326.64999999999947,
    "pct3ResTime" : 501.77999999999986,
    "throughput" : 0.11888231601772772,
    "receivedKBytesPerSec" : 1.9483232689545964,
    "sentKBytesPerSec" : 0.05224320528122801
  },
  "Tenders_Page/api/units/map/-51" : {
    "transaction" : "Tenders_Page/api/units/map/-51",
    "sampleCount" : 100,
    "errorCount" : 0,
    "errorPct" : 0.0,
    "meanResTime" : 2208.6400000000003,
    "medianResTime" : 863.5,
    "minResTime" : 82.0,
    "maxResTime" : 9934.0,
    "pct1ResTime" : 8947.1,
    "pct2ResTime" : 9412.149999999998,
    "pct3ResTime" : 9931.439999999999,
    "throughput" : 4.223686433519175,
    "receivedKBytesPerSec" : 24.958522079320833,
    "sentKBytesPerSec" : 1.9881024032775807
  },
  "Tenders_Page/maps/streets/256/8/150/89.png-90" : {
    "transaction" : "Tenders_Page/maps/streets/256/8/150/89.png-90",
    "sampleCount" : 100,
    "errorCount" : 0,
    "errorPct" : 0.0,
    "meanResTime" : 1433.04,
    "medianResTime" : 81.5,
    "minResTime" : 38.0,
    "maxResTime" : 131865.0,
    "pct1ResTime" : 241.0,
    "pct2ResTime" : 317.24999999999983,
    "pct3ResTime" : 130551.33999999933,
    "throughput" : 0.11889630933966179,
    "receivedKBytesPerSec" : 1.8313979367328959,
    "sentKBytesPerSec" : 0.05224935469028106
  },
  "Tenders_Page/maps/streets/256/8/147/89.png-97" : {
    "transaction" : "Tenders_Page/maps/streets/256/8/147/89.png-97",
    "sampleCount" : 100,
    "errorCount" : 0,
    "errorPct" : 0.0,
    "meanResTime" : 122.14000000000004,
    "medianResTime" : 78.0,
    "minResTime" : 37.0,
    "maxResTime" : 740.0,
    "pct1ResTime" : 224.9,
    "pct2ResTime" : 322.7499999999997,
    "pct3ResTime" : 737.1199999999985,
    "throughput" : 0.11885645824394338,
    "receivedKBytesPerSec" : 3.1211427365035522,
    "sentKBytesPerSec" : 0.05223184200173293
  },
  "Tenders_Page/tr/-77" : {
    "transaction" : "Tenders_Page/tr/-77",
    "sampleCount" : 100,
    "errorCount" : 41,
    "errorPct" : 41.0,
    "meanResTime" : 9262.01,
    "medianResTime" : 76.0,
    "minResTime" : 0.0,
    "maxResTime" : 291578.0,
    "pct1ResTime" : 3958.0,
    "pct2ResTime" : 66073.29999999996,
    "pct3ResTime" : 290352.50999999937,
    "throughput" : 0.1283140306259928,
    "receivedKBytesPerSec" : 0.1401993683260665,
    "sentKBytesPerSec" : 0.23409040348988502
  },
  "Tenders_Page/maps/streets/256/8/151/86.png-96" : {
    "transaction" : "Tenders_Page/maps/streets/256/8/151/86.png-96",
    "sampleCount" : 100,
    "errorCount" : 0,
    "errorPct" : 0.0,
    "meanResTime" : 164.13000000000002,
    "medianResTime" : 84.0,
    "minResTime" : 45.0,
    "maxResTime" : 5156.0,
    "pct1ResTime" : 223.60000000000014,
    "pct2ResTime" : 275.1499999999998,
    "pct3ResTime" : 5111.339999999977,
    "throughput" : 0.11888839352058256,
    "receivedKBytesPerSec" : 1.972107668301382,
    "sentKBytesPerSec" : 0.052245876058849755
  },
  "Tenders_Page/api/units/map/-53" : {
    "transaction" : "Tenders_Page/api/units/map/-53",
    "sampleCount" : 100,
    "errorCount" : 0,
    "errorPct" : 0.0,
    "meanResTime" : 1862.18,
    "medianResTime" : 1177.5,
    "minResTime" : 144.0,
    "maxResTime" : 9091.0,
    "pct1ResTime" : 3811.8000000000015,
    "pct2ResTime" : 7998.099999999984,
    "pct3ResTime" : 9088.14,
    "throughput" : 2.742130086651311,
    "receivedKBytesPerSec" : 16.203739408522537,
    "sentKBytesPerSec" : 1.2907292009432927
  },
  "Tenders_Page/maps/streets/256/8/151/89.png-98" : {
    "transaction" : "Tenders_Page/maps/streets/256/8/151/89.png-98",
    "sampleCount" : 100,
    "errorCount" : 0,
    "errorPct" : 0.0,
    "meanResTime" : 115.92000000000003,
    "medianResTime" : 69.5,
    "minResTime" : 41.0,
    "maxResTime" : 1017.0,
    "pct1ResTime" : 195.0,
    "pct2ResTime" : 253.2999999999996,
    "pct3ResTime" : 1013.7499999999984,
    "throughput" : 0.1188582947638167,
    "receivedKBytesPerSec" : 1.5992476418514319,
    "sentKBytesPerSec" : 0.05223264906613038
  },
  "Tenders_Page/maps/streets/256/8/147/87.png-91" : {
    "transaction" : "Tenders_Page/maps/streets/256/8/147/87.png-91",
    "sampleCount" : 100,
    "errorCount" : 1,
    "errorPct" : 1.0,
    "meanResTime" : 8040.4400000000005,
    "medianResTime" : 98.0,
    "minResTime" : 43.0,
    "maxResTime" : 360757.0,
    "pct1ResTime" : 297.9,
    "pct2ResTime" : 597.7499999999977,
    "pct3ResTime" : 359829.80999999953,
    "throughput" : 0.11889503708336206,
    "receivedKBytesPerSec" : 2.2601540170025847,
    "sentKBytesPerSec" : 0.0517263076373416
  },
  "Tenders_Page/maps/streets/256/8/147/88.png-93" : {
    "transaction" : "Tenders_Page/maps/streets/256/8/147/88.png-93",
    "sampleCount" : 100,
    "errorCount" : 0,
    "errorPct" : 0.0,
    "meanResTime" : 140.17999999999995,
    "medianResTime" : 85.0,
    "minResTime" : 40.0,
    "maxResTime" : 1013.0,
    "pct1ResTime" : 242.70000000000007,
    "pct2ResTime" : 480.9,
    "pct3ResTime" : 1010.7899999999988,
    "throughput" : 0.11888259867850104,
    "receivedKBytesPerSec" : 2.7858465213762797,
    "sentKBytesPerSec" : 0.05224332949738814
  },
  "Tenders_Page/api/units/map/-59" : {
    "transaction" : "Tenders_Page/api/units/map/-59",
    "sampleCount" : 100,
    "errorCount" : 52,
    "errorPct" : 52.0,
    "meanResTime" : 39234.399999999994,
    "medianResTime" : 60041.0,
    "minResTime" : 139.0,
    "maxResTime" : 60192.0,
    "pct1ResTime" : 60054.0,
    "pct2ResTime" : 60062.8,
    "pct3ResTime" : 60190.74,
    "throughput" : 0.3044408791034825,
    "receivedKBytesPerSec" : 0.917163824964761,
    "sentKBytesPerSec" : 0.14330127317175642
  },
  "Tenders_Page/api/units/map-user-coords_2/-49" : {
    "transaction" : "Tenders_Page/api/units/map-user-coords_2/-49",
    "sampleCount" : 100,
    "errorCount" : 0,
    "errorPct" : 0.0,
    "meanResTime" : 5188.809999999999,
    "medianResTime" : 1971.5,
    "minResTime" : 204.0,
    "maxResTime" : 14332.0,
    "pct1ResTime" : 13340.8,
    "pct2ResTime" : 13701.1,
    "pct3ResTime" : 14331.31,
    "throughput" : 4.612971676353907,
    "receivedKBytesPerSec" : 58.04505864240243,
    "sentKBytesPerSec" : 2.671379105544792
  },
  "Tenders_Page/api/units/map-user-coords_2/-58" : {
    "transaction" : "Tenders_Page/api/units/map-user-coords_2/-58",
    "sampleCount" : 100,
    "errorCount" : 79,
    "errorPct" : 79.0,
    "meanResTime" : 52532.660000000025,
    "medianResTime" : 60134.0,
    "minResTime" : 947.0,
    "maxResTime" : 60741.0,
    "pct1ResTime" : 60175.0,
    "pct2ResTime" : 60329.8,
    "pct3ResTime" : 60738.29,
    "throughput" : 0.25741615955683234,
    "receivedKBytesPerSec" : 0.7715521478482583,
    "sentKBytesPerSec" : 0.14982424911706257
  },
  "Tenders_Page/images/landlord-icon.svg-108" : {
    "transaction" : "Tenders_Page/images/landlord-icon.svg-108",
    "sampleCount" : 44,
    "errorCount" : 37,
    "errorPct" : 84.09091,
    "meanResTime" : 29921.840909090904,
    "medianResTime" : 5627.5,
    "minResTime" : 0.0,
    "maxResTime" : 62569.0,
    "pct1ResTime" : 62075.0,
    "pct2ResTime" : 62567.25,
    "pct3ResTime" : 62569.0,
    "throughput" : 0.028877359821747932,
    "receivedKBytesPerSec" : 0.06349609458319798,
    "sentKBytesPerSec" : 0.0020054434233453765
  },
  "Tenders_Page/api/units/map-user-coords_2/-52" : {
    "transaction" : "Tenders_Page/api/units/map-user-coords_2/-52",
    "sampleCount" : 100,
    "errorCount" : 0,
    "errorPct" : 0.0,
    "meanResTime" : 4962.799999999999,
    "medianResTime" : 4110.0,
    "minResTime" : 279.0,
    "maxResTime" : 13703.0,
    "pct1ResTime" : 12073.000000000004,
    "pct2ResTime" : 12773.85,
    "pct3ResTime" : 13697.249999999996,
    "throughput" : 2.875711738655317,
    "receivedKBytesPerSec" : 37.378635978029564,
    "sentKBytesPerSec" : 1.6737540978892276
  },
  "Tenders_Page/api/units/map-user-coords_2/-55" : {
    "transaction" : "Tenders_Page/api/units/map-user-coords_2/-55",
    "sampleCount" : 100,
    "errorCount" : 74,
    "errorPct" : 74.0,
    "meanResTime" : 48388.75,
    "medianResTime" : 60046.0,
    "minResTime" : 483.0,
    "maxResTime" : 60335.0,
    "pct1ResTime" : 60144.9,
    "pct2ResTime" : 60147.9,
    "pct3ResTime" : 60333.33,
    "throughput" : 0.3708689831143352,
    "receivedKBytesPerSec" : 1.3209237674169345,
    "sentKBytesPerSec" : 0.2680107885787188
  },
  "Tenders_Page/_next/image/-74" : {
    "transaction" : "Tenders_Page/_next/image/-74",
    "sampleCount" : 100,
    "errorCount" : 6,
    "errorPct" : 6.0,
    "meanResTime" : 89.03999999999999,
    "medianResTime" : 69.0,
    "minResTime" : 0.0,
    "maxResTime" : 545.0,
    "pct1ResTime" : 134.9,
    "pct2ResTime" : 173.1499999999998,
    "pct3ResTime" : 543.5799999999992,
    "throughput" : 0.17880419331594163,
    "receivedKBytesPerSec" : 2.919432450904839,
    "sentKBytesPerSec" : 0.08420210752032557
  },
  "Tenders_Page/api/units/map-user-coords_2/-99" : {
    "transaction" : "Tenders_Page/api/units/map-user-coords_2/-99",
    "sampleCount" : 100,
    "errorCount" : 100,
    "errorPct" : 100.0,
    "meanResTime" : 108136.57,
    "medianResTime" : 62837.5,
    "minResTime" : 60127.0,
    "maxResTime" : 1229006.0,
    "pct1ResTime" : 112015.90000000001,
    "pct2ResTime" : 113593.85,
    "pct3ResTime" : 1228925.22,
    "throughput" : 0.048723944261756726,
    "receivedKBytesPerSec" : 0.022198419644958365,
    "sentKBytesPerSec" : 0.026859074274293394
  },
  "Tenders_Page/api/units/map-user-coords_2/-54" : {
    "transaction" : "Tenders_Page/api/units/map-user-coords_2/-54",
    "sampleCount" : 100,
    "errorCount" : 22,
    "errorPct" : 22.0,
    "meanResTime" : 27450.8,
    "medianResTime" : 13351.5,
    "minResTime" : 329.0,
    "maxResTime" : 60253.0,
    "pct1ResTime" : 60131.0,
    "pct2ResTime" : 60179.7,
    "pct3ResTime" : 60252.89,
    "throughput" : 0.6655751234641855,
    "receivedKBytesPerSec" : 6.797536935259507,
    "sentKBytesPerSec" : 0.3873855210787641
  },
  "Tenders_Page/_next/image/-73" : {
    "transaction" : "Tenders_Page/_next/image/-73",
    "sampleCount" : 100,
    "errorCount" : 6,
    "errorPct" : 6.0,
    "meanResTime" : 151.35999999999999,
    "medianResTime" : 117.5,
    "minResTime" : 0.0,
    "maxResTime" : 795.0,
    "pct1ResTime" : 272.60000000000025,
    "pct2ResTime" : 340.09999999999957,
    "pct3ResTime" : 793.5599999999993,
    "throughput" : 0.1787089706541999,
    "receivedKBytesPerSec" : 5.579512214423065,
    "sentKBytesPerSec" : 0.0841572654578792
  },
  "Tenders_Page/v4/fullHashes:find-40" : {
    "transaction" : "Tenders_Page/v4/fullHashes:find-40",
    "sampleCount" : 100,
    "errorCount" : 0,
    "errorPct" : 0.0,
    "meanResTime" : 671.81,
    "medianResTime" : 625.0,
    "minResTime" : 237.0,
    "maxResTime" : 1786.0,
    "pct1ResTime" : 1027.4,
    "pct2ResTime" : 1269.7499999999998,
    "pct3ResTime" : 1782.4199999999983,
    "throughput" : 9.986019572598362,
    "receivedKBytesPerSec" : 5.695151787497504,
    "sentKBytesPerSec" : 6.602085205712004
  },
  "Tenders_Page/_next/image/-72" : {
    "transaction" : "Tenders_Page/_next/image/-72",
    "sampleCount" : 100,
    "errorCount" : 6,
    "errorPct" : 6.0,
    "meanResTime" : 127.28999999999994,
    "medianResTime" : 99.0,
    "minResTime" : 0.0,
    "maxResTime" : 1021.0,
    "pct1ResTime" : 188.60000000000002,
    "pct2ResTime" : 266.7499999999997,
    "pct3ResTime" : 1020.8199999999999,
    "throughput" : 0.1781375364291262,
    "receivedKBytesPerSec" : 2.5871728559811458,
    "sentKBytesPerSec" : 0.08405169150497716
  },
  "Tenders_Page/_next/image/-71" : {
    "transaction" : "Tenders_Page/_next/image/-71",
    "sampleCount" : 100,
    "errorCount" : 6,
    "errorPct" : 6.0,
    "meanResTime" : 81.21999999999997,
    "medianResTime" : 58.0,
    "minResTime" : 0.0,
    "maxResTime" : 1056.0,
    "pct1ResTime" : 134.8,
    "pct2ResTime" : 186.64999999999992,
    "pct3ResTime" : 1047.5399999999956,
    "throughput" : 0.17807726416337522,
    "receivedKBytesPerSec" : 1.9306131817910657,
    "sentKBytesPerSec" : 0.08418672224754876
  },
  "Tenders_Page/_next/image/-70" : {
    "transaction" : "Tenders_Page/_next/image/-70",
    "sampleCount" : 100,
    "errorCount" : 6,
    "errorPct" : 6.0,
    "meanResTime" : 111.58999999999997,
    "medianResTime" : 67.0,
    "minResTime" : 0.0,
    "maxResTime" : 731.0,
    "pct1ResTime" : 212.0,
    "pct2ResTime" : 446.74999999999903,
    "pct3ResTime" : 730.3599999999997,
    "throughput" : 0.17839303553589267,
    "receivedKBytesPerSec" : 2.548083194707079,
    "sentKBytesPerSec" : 0.08417224516554875
  },
  "Tenders_Page/maps/streets/256/8/148/87.png-83" : {
    "transaction" : "Tenders_Page/maps/streets/256/8/148/87.png-83",
    "sampleCount" : 100,
    "errorCount" : 0,
    "errorPct" : 0.0,
    "meanResTime" : 160.65999999999997,
    "medianResTime" : 111.0,
    "minResTime" : 39.0,
    "maxResTime" : 1576.0,
    "pct1ResTime" : 307.00000000000006,
    "pct2ResTime" : 437.699999999999,
    "pct3ResTime" : 1565.9299999999948,
    "throughput" : 0.11893166067845756,
    "receivedKBytesPerSec" : 2.527297789417223,
    "sentKBytesPerSec" : 0.052264889946587796
  },
  "Tenders_Page/api/units/map-user-coords_2/-50" : {
    "transaction" : "Tenders_Page/api/units/map-user-coords_2/-50",
    "sampleCount" : 100,
    "errorCount" : 1,
    "errorPct" : 1.0,
    "meanResTime" : 12885.04,
    "medianResTime" : 10817.5,
    "minResTime" : 368.0,
    "maxResTime" : 60052.0,
    "pct1ResTime" : 35802.60000000009,
    "pct2ResTime" : 54015.399999999994,
    "pct3ResTime" : 60007.449999999975,
    "throughput" : 1.1067946121238281,
    "receivedKBytesPerSec" : 14.246057130662638,
    "sentKBytesPerSec" : 0.6441890515876969
  },
  "Tenders_Page/maps/streets/256/8/148/89.png-89" : {
    "transaction" : "Tenders_Page/maps/streets/256/8/148/89.png-89",
    "sampleCount" : 100,
    "errorCount" : 0,
    "errorPct" : 0.0,
    "meanResTime" : 3420.720000000002,
    "medianResTime" : 103.0,
    "minResTime" : 44.0,
    "maxResTime" : 163112.0,
    "pct1ResTime" : 320.6000000000001,
    "pct2ResTime" : 24004.949999999717,
    "pct3ResTime" : 162035.42999999947,
    "throughput" : 0.11889630933966179,
    "receivedKBytesPerSec" : 3.1661947845539427,
    "sentKBytesPerSec" : 0.05224935469028106
  },
  "Tenders_Page/maps/streets/256/8/149/87.png-79" : {
    "transaction" : "Tenders_Page/maps/streets/256/8/149/87.png-79",
    "sampleCount" : 100,
    "errorCount" : 37,
    "errorPct" : 37.0,
    "meanResTime" : 83277.33999999998,
    "medianResTime" : 68822.5,
    "minResTime" : 101.0,
    "maxResTime" : 219322.0,
    "pct1ResTime" : 173421.5,
    "pct2ResTime" : 173444.0,
    "pct3ResTime" : 219321.21,
    "throughput" : 0.1189271345339424,
    "receivedKBytesPerSec" : 1.5998893438760255,
    "sentKBytesPerSec" : 0.032925627578488936
  },
  "Tenders_Page/maps/streets/256/9/297/172.png-30" : {
    "transaction" : "Tenders_Page/maps/streets/256/9/297/172.png-30",
    "sampleCount" : 100,
    "errorCount" : 0,
    "errorPct" : 0.0,
    "meanResTime" : 164.77,
    "medianResTime" : 141.5,
    "minResTime" : 44.0,
    "maxResTime" : 580.0,
    "pct1ResTime" : 267.9,
    "pct2ResTime" : 494.95,
    "pct3ResTime" : 579.89,
    "throughput" : 45.662100456621005,
    "receivedKBytesPerSec" : 611.6224315068494,
    "sentKBytesPerSec" : 20.1109446347032
  },
  "Tenders_Page/maps/streets/256/11/1196/690.png-41" : {
    "transaction" : "Tenders_Page/maps/streets/256/11/1196/690.png-41",
    "sampleCount" : 100,
    "errorCount" : 0,
    "errorPct" : 0.0,
    "meanResTime" : 534.7700000000003,
    "medianResTime" : 490.5,
    "minResTime" : 67.0,
    "maxResTime" : 1997.0,
    "pct1ResTime" : 824.5000000000002,
    "pct2ResTime" : 1365.799999999999,
    "pct3ResTime" : 1996.95,
    "throughput" : 9.799118079372857,
    "receivedKBytesPerSec" : 216.0877786624204,
    "sentKBytesPerSec" : 4.334961415972562
  },
  "Tenders_Page/maps/streets/256/11/1196/689.png-45" : {
    "transaction" : "Tenders_Page/maps/streets/256/11/1196/689.png-45",
    "sampleCount" : 100,
    "errorCount" : 0,
    "errorPct" : 0.0,
    "meanResTime" : 465.04,
    "medianResTime" : 403.0,
    "minResTime" : 129.0,
    "maxResTime" : 1476.0,
    "pct1ResTime" : 940.3000000000003,
    "pct2ResTime" : 1242.5999999999979,
    "pct3ResTime" : 1475.2399999999996,
    "throughput" : 10.158472165786264,
    "receivedKBytesPerSec" : 154.51988520926454,
    "sentKBytesPerSec" : 4.493933487403495
  },
  "Tenders_Page/maps/streets/256/11/1198/690.png-35" : {
    "transaction" : "Tenders_Page/maps/streets/256/11/1198/690.png-35",
    "sampleCount" : 100,
    "errorCount" : 0,
    "errorPct" : 0.0,
    "meanResTime" : 410.62,
    "medianResTime" : 320.0,
    "minResTime" : 64.0,
    "maxResTime" : 1364.0,
    "pct1ResTime" : 884.9,
    "pct2ResTime" : 1091.75,
    "pct3ResTime" : 1363.79,
    "throughput" : 12.205541315757355,
    "receivedKBytesPerSec" : 209.15100924569757,
    "sentKBytesPerSec" : 5.399521695349689
  },
  "Tenders_Page/maps/streets/256/11/1198/689.png-37" : {
    "transaction" : "Tenders_Page/maps/streets/256/11/1198/689.png-37",
    "sampleCount" : 100,
    "errorCount" : 0,
    "errorPct" : 0.0,
    "meanResTime" : 478.81,
    "medianResTime" : 350.5,
    "minResTime" : 50.0,
    "maxResTime" : 2013.0,
    "pct1ResTime" : 1035.8000000000002,
    "pct2ResTime" : 1463.8499999999997,
    "pct3ResTime" : 2012.87,
    "throughput" : 11.345586566825505,
    "receivedKBytesPerSec" : 170.4275513387792,
    "sentKBytesPerSec" : 5.019092494894486
  },
  "Tenders_Page/_next/data/agFThXjCqXxZlEtNEZYm2/shepovoz-zernovoz/730/unit.json-103" : {
    "transaction" : "Tenders_Page/_next/data/agFThXjCqXxZlEtNEZYm2/shepovoz-zernovoz/730/unit.json-103",
    "sampleCount" : 89,
    "errorCount" : 89,
    "errorPct" : 100.0,
    "meanResTime" : 226375.595505618,
    "medianResTime" : 31246.0,
    "minResTime" : 0.0,
    "maxResTime" : 1213927.0,
    "pct1ResTime" : 1213390.0,
    "pct2ResTime" : 1213684.0,
    "pct3ResTime" : 1213927.0,
    "throughput" : 0.0460837844625155,
    "receivedKBytesPerSec" : 0.2713328440167455,
    "sentKBytesPerSec" : 0.014101832218778882
  },
  "Tenders_Page/maps/streets/256/11/1199/691.png-48" : {
    "transaction" : "Tenders_Page/maps/streets/256/11/1199/691.png-48",
    "sampleCount" : 100,
    "errorCount" : 0,
    "errorPct" : 0.0,
    "meanResTime" : 285.6100000000001,
    "medianResTime" : 221.5,
    "minResTime" : 69.0,
    "maxResTime" : 1514.0,
    "pct1ResTime" : 527.3000000000002,
    "pct2ResTime" : 647.2499999999998,
    "pct3ResTime" : 1507.1899999999964,
    "throughput" : 11.380448389666553,
    "receivedKBytesPerSec" : 153.5915983839763,
    "sentKBytesPerSec" : 5.034514766131785
  },
  "Tenders_Page/_next/image/-43" : {
    "transaction" : "Tenders_Page/_next/image/-43",
    "sampleCount" : 100,
    "errorCount" : 0,
    "errorPct" : 0.0,
    "meanResTime" : 343.52999999999986,
    "medianResTime" : 288.5,
    "minResTime" : 110.0,
    "maxResTime" : 899.0,
    "pct1ResTime" : 660.2,
    "pct2ResTime" : 799.7499999999995,
    "pct3ResTime" : 898.2899999999996,
    "throughput" : 11.12099644128114,
    "receivedKBytesPerSec" : 285.68840705627224,
    "sentKBytesPerSec" : 5.582218916814946
  },
  "Tenders_Page/_next/image/-42" : {
    "transaction" : "Tenders_Page/_next/image/-42",
    "sampleCount" : 100,
    "errorCount" : 0,
    "errorPct" : 0.0,
    "meanResTime" : 261.8099999999999,
    "medianResTime" : 164.5,
    "minResTime" : 54.0,
    "maxResTime" : 907.0,
    "pct1ResTime" : 600.0000000000001,
    "pct2ResTime" : 834.0,
    "pct3ResTime" : 907.0,
    "throughput" : 11.016855789357717,
    "receivedKBytesPerSec" : 128.1592770532665,
    "sentKBytesPerSec" : 5.529945191142448
  },
  "Tenders_Page/api/units/map-user-coords_2/-66" : {
    "transaction" : "Tenders_Page/api/units/map-user-coords_2/-66",
    "sampleCount" : 100,
    "errorCount" : 96,
    "errorPct" : 96.0,
    "meanResTime" : 57957.01,
    "medianResTime" : 60049.5,
    "minResTime" : 4098.0,
    "maxResTime" : 61308.0,
    "pct1ResTime" : 60077.9,
    "pct2ResTime" : 60148.75,
    "pct3ResTime" : 61301.14,
    "throughput" : 0.17644899918127666,
    "receivedKBytesPerSec" : 0.15065711812907598,
    "sentKBytesPerSec" : 0.09649554642726067
  },
  "Tenders_Page/api/units/map-user-coords_2/-60" : {
    "transaction" : "Tenders_Page/api/units/map-user-coords_2/-60",
    "sampleCount" : 100,
    "errorCount" : 90,
    "errorPct" : 90.0,
    "meanResTime" : 55941.42999999999,
    "medianResTime" : 60150.0,
    "minResTime" : 1423.0,
    "maxResTime" : 60986.0,
    "pct1ResTime" : 60280.0,
    "pct2ResTime" : 60289.0,
    "pct3ResTime" : 60979.67,
    "throughput" : 0.2233349264558087,
    "receivedKBytesPerSec" : 0.35840457484846727,
    "sentKBytesPerSec" : 0.12998790641373242
  },
  "Tenders_Page/maps/streets/256/11/1197/691.png-38" : {
    "transaction" : "Tenders_Page/maps/streets/256/11/1197/691.png-38",
    "sampleCount" : 100,
    "errorCount" : 0,
    "errorPct" : 0.0,
    "meanResTime" : 511.87000000000006,
    "medianResTime" : 479.5,
    "minResTime" : 101.0,
    "maxResTime" : 1600.0,
    "pct1ResTime" : 1002.8000000000002,
    "pct2ResTime" : 1125.499999999999,
    "pct3ResTime" : 1597.6199999999988,
    "throughput" : 10.54629824931449,
    "receivedKBytesPerSec" : 252.80218440202492,
    "sentKBytesPerSec" : 4.665501080995571
  },
  "Tenders_Page/api/units/map-user-coords_2/-61" : {
    "transaction" : "Tenders_Page/api/units/map-user-coords_2/-61",
    "sampleCount" : 100,
    "errorCount" : 93,
    "errorPct" : 93.0,
    "meanResTime" : 57292.05999999999,
    "medianResTime" : 60150.0,
    "minResTime" : 3092.0,
    "maxResTime" : 60878.0,
    "pct1ResTime" : 60255.6,
    "pct2ResTime" : 60632.45,
    "pct3ResTime" : 60877.9,
    "throughput" : 0.19716010583554483,
    "receivedKBytesPerSec" : 0.24412425917090233,
    "sentKBytesPerSec" : 0.10782193287881357
  },
  "Tenders_Page/maps/streets/256/11/1197/690.png-34" : {
    "transaction" : "Tenders_Page/maps/streets/256/11/1197/690.png-34",
    "sampleCount" : 100,
    "errorCount" : 0,
    "errorPct" : 0.0,
    "meanResTime" : 615.17,
    "medianResTime" : 466.5,
    "minResTime" : 67.0,
    "maxResTime" : 3535.0,
    "pct1ResTime" : 1492.1000000000004,
    "pct2ResTime" : 1563.7999999999997,
    "pct3ResTime" : 3520.4999999999927,
    "throughput" : 13.056534795665229,
    "receivedKBytesPerSec" : 376.76518230186707,
    "sentKBytesPerSec" : 5.775986584410497
  },
  "Tenders_Page/maps/streets/256/11/1199/690.png-44" : {
    "transaction" : "Tenders_Page/maps/streets/256/11/1199/690.png-44",
    "sampleCount" : 100,
    "errorCount" : 0,
    "errorPct" : 0.0,
    "meanResTime" : 317.75999999999993,
    "medianResTime" : 299.0,
    "minResTime" : 63.0,
    "maxResTime" : 881.0,
    "pct1ResTime" : 525.2000000000002,
    "pct2ResTime" : 703.2999999999987,
    "pct3ResTime" : 879.8599999999994,
    "throughput" : 10.71007818357074,
    "receivedKBytesPerSec" : 133.29026989397022,
    "sentKBytesPerSec" : 4.737954508942916
  },
  "Tenders_Page/maps/streets/256/8/148/86.png-87" : {
    "transaction" : "Tenders_Page/maps/streets/256/8/148/86.png-87",
    "sampleCount" : 100,
    "errorCount" : 0,
    "errorPct" : 0.0,
    "meanResTime" : 1082.98,
    "medianResTime" : 93.5,
    "minResTime" : 39.0,
    "maxResTime" : 55098.0,
    "pct1ResTime" : 300.8,
    "pct2ResTime" : 459.599999999999,
    "pct3ResTime" : 54947.59999999992,
    "throughput" : 0.11889715752565504,
    "receivedKBytesPerSec" : 2.416956280326206,
    "sentKBytesPerSec" : 0.052249727428266377
  },
  "Tenders_Page/_next/image/-101" : {
    "transaction" : "Tenders_Page/_next/image/-101",
    "sampleCount" : 94,
    "errorCount" : 9,
    "errorPct" : 9.574468,
    "meanResTime" : 89050.6595744681,
    "medianResTime" : 5900.0,
    "minResTime" : 99.0,
    "maxResTime" : 1355998.0,
    "pct1ResTime" : 93814.0,
    "pct2ResTime" : 1193832.25,
    "pct3ResTime" : 1355998.0,
    "throughput" : 0.0471946543518743,
    "receivedKBytesPerSec" : 1.2803388631096457,
    "sentKBytesPerSec" : 0.021463036010776447
  },
  "Tenders_Page/api/units/map/-76" : {
    "transaction" : "Tenders_Page/api/units/map/-76",
    "sampleCount" : 100,
    "errorCount" : 96,
    "errorPct" : 96.0,
    "meanResTime" : 54463.06000000003,
    "medianResTime" : 60050.0,
    "minResTime" : 0.0,
    "maxResTime" : 62170.0,
    "pct1ResTime" : 60297.2,
    "pct2ResTime" : 60736.75,
    "pct3ResTime" : 62166.619999999995,
    "throughput" : 0.16222836887486514,
    "receivedKBytesPerSec" : 0.10774561882011308,
    "sentKBytesPerSec" : 0.07177971618146865
  },
  "Tenders_Page/_next/image/-100" : {
    "transaction" : "Tenders_Page/_next/image/-100",
    "sampleCount" : 97,
    "errorCount" : 5,
    "errorPct" : 5.1546392,
    "meanResTime" : 73474.09278350516,
    "medianResTime" : 4445.0,
    "minResTime" : 171.0,
    "maxResTime" : 1334187.0,
    "pct1ResTime" : 111790.40000000002,
    "pct2ResTime" : 200163.8999999982,
    "pct3ResTime" : 1334187.0,
    "throughput" : 0.04868945065248883,
    "receivedKBytesPerSec" : 0.7205139690724107,
    "sentKBytesPerSec" : 0.023180037275037167
  },
  "Tenders_Page/api/units/map-user-coords_2/-102" : {
    "transaction" : "Tenders_Page/api/units/map-user-coords_2/-102",
    "sampleCount" : 89,
    "errorCount" : 89,
    "errorPct" : 100.0,
    "meanResTime" : 90642.75280898878,
    "medianResTime" : 72895.0,
    "minResTime" : 60040.0,
    "maxResTime" : 484506.0,
    "pct1ResTime" : 87212.0,
    "pct2ResTime" : 292926.5,
    "pct3ResTime" : 484506.0,
    "throughput" : 0.06109737754952835,
    "receivedKBytesPerSec" : 0.0380832900989297,
    "sentKBytesPerSec" : 0.03156501190025887
  },
  "Tenders_Page/maps/streets/256/9/297/171.png-32" : {
    "transaction" : "Tenders_Page/maps/streets/256/9/297/171.png-32",
    "sampleCount" : 100,
    "errorCount" : 0,
    "errorPct" : 0.0,
    "meanResTime" : 200.15999999999994,
    "medianResTime" : 155.5,
    "minResTime" : 58.0,
    "maxResTime" : 1053.0,
    "pct1ResTime" : 354.5000000000001,
    "pct2ResTime" : 537.2999999999994,
    "pct3ResTime" : 1051.019999999999,
    "throughput" : 33.04692663582287,
    "receivedKBytesPerSec" : 379.6523876404495,
    "sentKBytesPerSec" : 14.554847571050892
  },
  "Tenders_Page/_next/image/-57" : {
    "transaction" : "Tenders_Page/_next/image/-57",
    "sampleCount" : 100,
    "errorCount" : 0,
    "errorPct" : 0.0,
    "meanResTime" : 254.46999999999994,
    "medianResTime" : 243.5,
    "minResTime" : 140.0,
    "maxResTime" : 755.0,
    "pct1ResTime" : 304.8,
    "pct2ResTime" : 375.6499999999999,
    "pct3ResTime" : 751.9099999999985,
    "throughput" : 0.37181217536149436,
    "receivedKBytesPerSec" : 14.865918574760276,
    "sentKBytesPerSec" : 0.1869953811632516
  },
  "Tenders_Page/api/units/map-user-coords_2/-78" : {
    "transaction" : "Tenders_Page/api/units/map-user-coords_2/-78",
    "sampleCount" : 100,
    "errorCount" : 100,
    "errorPct" : 100.0,
    "meanResTime" : 45854.450000000004,
    "medianResTime" : 60155.0,
    "minResTime" : 0.0,
    "maxResTime" : 121051.0,
    "pct1ResTime" : 60665.1,
    "pct2ResTime" : 61170.95,
    "pct3ResTime" : 120475.6199999997,
    "throughput" : 0.11109136153572699,
    "receivedKBytesPerSec" : 0.08550671720860736,
    "sentKBytesPerSec" : 0.048493983014130826
  },
  "Tenders_Page/api/units/map-user-coords_2/-75" : {
    "transaction" : "Tenders_Page/api/units/map-user-coords_2/-75",
    "sampleCount" : 100,
    "errorCount" : 97,
    "errorPct" : 97.0,
    "meanResTime" : 48961.259999999995,
    "medianResTime" : 60188.5,
    "minResTime" : 0.0,
    "maxResTime" : 68590.0,
    "pct1ResTime" : 61548.9,
    "pct2ResTime" : 64965.049999999996,
    "pct3ResTime" : 68585.45,
    "throughput" : 0.16452401557055282,
    "receivedKBytesPerSec" : 0.1692926413343556,
    "sentKBytesPerSec" : 0.07852165711878964
  },
  "Tenders_Page/api/units/map-user-coords_2/-33" : {
    "transaction" : "Tenders_Page/api/units/map-user-coords_2/-33",
    "sampleCount" : 100,
    "errorCount" : 0,
    "errorPct" : 0.0,
    "meanResTime" : 1951.6899999999996,
    "medianResTime" : 1978.0,
    "minResTime" : 516.0,
    "maxResTime" : 3277.0,
    "pct1ResTime" : 2853.1,
    "pct2ResTime" : 3037.4999999999995,
    "pct3ResTime" : 3276.1399999999994,
    "throughput" : 17.070672584499828,
    "receivedKBytesPerSec" : 215.63393543018097,
    "sentKBytesPerSec" : 9.935664902697168
  },
  "Tenders_Page/maps/streets/256/8/148/88.png-82" : {
    "transaction" : "Tenders_Page/maps/streets/256/8/148/88.png-82",
    "sampleCount" : 100,
    "errorCount" : 0,
    "errorPct" : 0.0,
    "meanResTime" : 3874.6599999999994,
    "medianResTime" : 147.5,
    "minResTime" : 43.0,
    "maxResTime" : 327454.0,
    "pct1ResTime" : 2587.8,
    "pct2ResTime" : 2944.699999999997,
    "pct3ResTime" : 324217.9399999984,
    "throughput" : 0.11893364097501799,
    "receivedKBytesPerSec" : 2.5732175935561754,
    "sentKBytesPerSec" : 0.0522657601940997
  },
  "Tenders_Page/api/auth/users/348/-105" : {
    "transaction" : "Tenders_Page/api/auth/users/348/-105",
    "sampleCount" : 74,
    "errorCount" : 74,
    "errorPct" : 100.0,
    "meanResTime" : 250306.91891891893,
    "medianResTime" : 62040.0,
    "minResTime" : 0.0,
    "maxResTime" : 1182228.0,
    "pct1ResTime" : 1182180.0,
    "pct2ResTime" : 1182202.75,
    "pct3ResTime" : 1182228.0,
    "throughput" : 0.03833471908162446,
    "receivedKBytesPerSec" : 0.06487701969575702,
    "sentKBytesPerSec" : 0.00768859613337374
  },
  "Tenders_Page/tr/-65" : {
    "transaction" : "Tenders_Page/tr/-65",
    "sampleCount" : 100,
    "errorCount" : 0,
    "errorPct" : 0.0,
    "meanResTime" : 373.81,
    "medianResTime" : 91.5,
    "minResTime" : 63.0,
    "maxResTime" : 5552.0,
    "pct1ResTime" : 284.3000000000003,
    "pct2ResTime" : 3266.85,
    "pct3ResTime" : 5536.759999999992,
    "throughput" : 0.19710103793406575,
    "receivedKBytesPerSec" : 0.07314296329584472,
    "sentKBytesPerSec" : 0.6128071450111756
  },
  "Tenders_Page/_next/image/-110" : {
    "transaction" : "Tenders_Page/_next/image/-110",
    "sampleCount" : 44,
    "errorCount" : 37,
    "errorPct" : 84.09091,
    "meanResTime" : 29645.272727272724,
    "medianResTime" : 82.5,
    "minResTime" : 0.0,
    "maxResTime" : 63092.0,
    "pct1ResTime" : 62072.0,
    "pct2ResTime" : 62075.75,
    "pct3ResTime" : 63092.0,
    "throughput" : 0.025736472559071053,
    "receivedKBytesPerSec" : 0.05836688792965286,
    "sentKBytesPerSec" : 0.002523037981476759
  },
  "Tenders_Page/maps/streets/256/8/150/87.png-81" : {
    "transaction" : "Tenders_Page/maps/streets/256/8/150/87.png-81",
    "sampleCount" : 100,
    "errorCount" : 0,
    "errorPct" : 0.0,
    "meanResTime" : 573.2700000000002,
    "medianResTime" : 103.0,
    "minResTime" : 44.0,
    "maxResTime" : 40243.0,
    "pct1ResTime" : 347.2000000000003,
    "pct2ResTime" : 604.6999999999988,
    "pct3ResTime" : 39858.2699999998,
    "throughput" : 0.11889927804358372,
    "receivedKBytesPerSec" : 2.7609248372268884,
    "sentKBytesPerSec" : 0.05225065929649675
  },
  "Tenders_Page/maps/streets/256/9/298/171.png-29" : {
    "transaction" : "Tenders_Page/maps/streets/256/9/298/171.png-29",
    "sampleCount" : 100,
    "errorCount" : 0,
    "errorPct" : 0.0,
    "meanResTime" : 434.8400000000001,
    "medianResTime" : 406.5,
    "minResTime" : 150.0,
    "maxResTime" : 1185.0,
    "pct1ResTime" : 629.2,
    "pct2ResTime" : 984.0999999999987,
    "pct3ResTime" : 1184.1699999999996,
    "throughput" : 51.89413596263622,
    "receivedKBytesPerSec" : 643.1021341463414,
    "sentKBytesPerSec" : 22.855718085106382
  },
  "Total" : {
    "transaction" : "Total",
    "sampleCount" : 7855,
    "errorCount" : 1534,
    "errorPct" : 19.528963,
    "meanResTime" : 21475.364099299823,
    "medianResTime" : 268.0,
    "minResTime" : 0.0,
    "maxResTime" : 1355998.0,
    "pct1ResTime" : 60147.0,
    "pct2ResTime" : 62039.0,
    "pct3ResTime" : 173438.4,
    "throughput" : 3.629370781231879,
    "receivedKBytesPerSec" : 51.209967257692725,
    "sentKBytesPerSec" : 1.8590025440537694
  },
  "Tenders_Page/maps/streets/256/9/297/173.png-31" : {
    "transaction" : "Tenders_Page/maps/streets/256/9/297/173.png-31",
    "sampleCount" : 100,
    "errorCount" : 0,
    "errorPct" : 0.0,
    "meanResTime" : 178.16,
    "medianResTime" : 153.0,
    "minResTime" : 55.0,
    "maxResTime" : 741.0,
    "pct1ResTime" : 281.30000000000007,
    "pct2ResTime" : 499.1499999999996,
    "pct3ResTime" : 739.3299999999991,
    "throughput" : 37.18854592785422,
    "receivedKBytesPerSec" : 434.2416441985868,
    "sentKBytesPerSec" : 16.37893966158423
  },
  "Tenders_Page/maps/streets/256/11/1198/691.png-39" : {
    "transaction" : "Tenders_Page/maps/streets/256/11/1198/691.png-39",
    "sampleCount" : 100,
    "errorCount" : 0,
    "errorPct" : 0.0,
    "meanResTime" : 534.6299999999999,
    "medianResTime" : 367.5,
    "minResTime" : 46.0,
    "maxResTime" : 2593.0,
    "pct1ResTime" : 1286.6000000000001,
    "pct2ResTime" : 1442.2999999999997,
    "pct3ResTime" : 2582.6499999999946,
    "throughput" : 14.894250819183794,
    "receivedKBytesPerSec" : 279.3253835269586,
    "sentKBytesPerSec" : 6.588960567470956
  },
  "Tenders_Page/maps/streets/256/11/1196/691.png-47" : {
    "transaction" : "Tenders_Page/maps/streets/256/11/1196/691.png-47",
    "sampleCount" : 100,
    "errorCount" : 0,
    "errorPct" : 0.0,
    "meanResTime" : 403.54,
    "medianResTime" : 352.5,
    "minResTime" : 82.0,
    "maxResTime" : 1481.0,
    "pct1ResTime" : 531.0,
    "pct2ResTime" : 941.1999999999989,
    "pct3ResTime" : 1480.82,
    "throughput" : 10.482180293501049,
    "receivedKBytesPerSec" : 181.5955843815514,
    "sentKBytesPerSec" : 4.6371363993710695
  }
}